<?xml version="1.0" encoding="iso-8859-1"?>
<Application>
	<GUID>dd15f277-b579-4753-b1-bd-58-84-9e-04-3b</GUID>
	<Name>BaseEngineController_A02_bak2</Name>
	<Author>maxar</Author>
	<Copyright>2019 Woodward.</Copyright>
	<CreateDate>01-Jan-2019</CreateDate>
	<MemoryLayout>DEV</MemoryLayout>
	<Module>ClassicModule-MPC555</Module>
	<Memory/>
	<Types/>
	<ToolInterface>
		<KeySuite>
			<CAN ref="CAN_1">
				<CityID>11</CityID>
			</CAN>
		</KeySuite>
		<VarDecs>
			<TableDatabase>
				<MaxTableSize>65535</MaxTableSize>
				<Table0Revision>9</Table0Revision>
				<HeaderFile>CommonInclude.h</HeaderFile>
				<HeaderFile>BaseEngineController_A02_bak2.h</HeaderFile>
				<Include name="*" location="1,0"/>
			</TableDatabase>
			<ProjectID>6</ProjectID>
			<ProductID>1</ProductID>
			<SwIdTxt>BaseEngin_119</SwIdTxt>
			<SwRevisionTxt>BaseEngineController_A02_bak2_119</SwRevisionTxt>
			<CalIdTxt>BaseEngineController_A02_bak2_119_000</CalIdTxt>
		</VarDecs>
		<DatabaseBuild>
			<Toolchain>
				<Vendor>gcc-win32-pe</Vendor>
				<Product>win32-pe</Product>
				<Version>4.4.0</Version>
				<InstallDirectory>C:\Program Files (x86)\Woodward\DevelopmentTools\Toolchains\GCC\win32-pe\4_4_0\</InstallDirectory>
			</Toolchain>
		</DatabaseBuild>
		<Command>
			<Description>Copy BaseEngin_119.dll and BaseEngineController_A02_bak2_119.srz</Description>
			<Order>99</Order>
			<Execute>@if exist C:\ECUFiles\TDBDLL\\*.* copy /Y .\TDB\BaseEngin_119.dll C:\ECUFiles\TDBDLL\ &gt; NUL</Execute>
			<Execute>@if exist C:\ECUFiles\Programs\*.* copy /Y .\Target\BaseEngineController_A02_bak2_119.srz C:\ECUFiles\Programs &gt; NUL</Execute>
		</Command>
	</ToolInterface>
	<Build>
		<Toolchain>
			<Vendor>gcc-powerpc-eabi</Vendor>
			<Product>powerpc-eabi</Product>
			<Version>4.4.0</Version>
			<ArchiveExtension>a</ArchiveExtension>
			<InstallDirectory>C:\Program Files (x86)\Woodward\DevelopmentTools\Toolchains\GCC\powerpc-eabi\4_4_0\</InstallDirectory>
		</Toolchain>
		<Directory>.</Directory>
		<Target>
			<Directory>.\Target</Directory>
		</Target>
		<Source>
			<File>AppMonitor.c</File>
			<File>Application.c</File>
			<File>ApplicationSecurity.c</File>
			<File>BaseEngineController_A02_bak2_IdleStateMachine.c</File>
			<File>BaseEngineController_A02_bak2_data.c</File>
			<File>EncoderCallback.c</File>
			<File>FaultManager.c</File>
			<File>Foreground.c</File>
			<File>IOCallbacks.c</File>
			<File>InjectorSequenceCallback_43.c</File>
			<File>MotoHawk_CAN.c</File>
			<File>MotoHawk_DataStores.c</File>
			<File>MotoHawk_IO.c</File>
			<File>TableLookupFunctions.c</File>
			<File>Trigger_BGND_BASE_PERIODIC_9866p0001.c</File>
			<File>Trigger_Encoder_Fault_33.c</File>
			<File>Trigger_FGND_5XRTI_PERIODIC_1236p0004.c</File>
			<File>Trigger_FGND_5XRTI_PERIODIC_1237p0004.c</File>
			<File>Trigger_FGND_5XRTI_PERIODIC_4926p0004.c</File>
			<File>Trigger_FGND_5XRTI_PERIODIC_8535p0002.c</File>
			<File>Trigger_FGND_5XRTI_PERIODIC_9590p0004.c</File>
			<File>Trigger_FGND_MID_TDC_EVENT_8346p0002.c</File>
			<File>Trigger_FGND_RTI_PERIODIC_9872p0001.c</File>
			<File>Trigger_FGND_TDC1_EVENT_984p0004.c</File>
			<File>Trigger_FGND_TDC_EVENT_7146p0001.c</File>
			<File>Trigger_FGND_TDC_EVENT_9072p0002.c</File>
			<File>Trigger_STARTUP_EVENT_8345p0002.c</File>
			<File>VarDecs.c</File>
			<File>rt_zcfcn.c</File>
			<File>rt_nonfinite.c</File>
			<File>BaseEngineController_A02_bak2.c</File>
		</Source>
		<Header>
			<Directory>.</Directory>
		</Header>
		<Header>
			<Directory>C:\ProgramData\MotoHawk\2011a_sp0_184\Toolchains\7_12_0\rtw_lib_single\API</Directory>
			<Directory>C:\ProgramData\MotoHawk\2011a_sp0_184\Toolchains\7_12_0\rtw_lib_single\API\MPC555</Directory>
		</Header>
		<Library>
			<Directory>C:\Program Files (x86)\Woodward\MCS\MotoHawk\2011a_sp0.184\MotoCoder\..\ControlCoreClassic\Framework\MultiTask\Archives\gcc-powerpc-eabi\4_4_0</Directory>
			<File>PCM</File>
		</Library>
		<Command>
			<Execute>@copy "LinkerDefinition_DEV.xml" "LinkerDefinition.xml" &gt; NUL</Execute>
			<Execute>@copy "BaseEngineController_A02_bak2_DEV.ld" "BaseEngineController_A02_bak2.ld" &gt; NUL</Execute>
			<Order>0</Order>
		</Command>
		<Command>
			<Description>Call MotoConvert</Description>
			<Execute>@"%MOTOCODER_DIR%\bin\MotoConvert.exe" -project=MPC5xx -map=.\Target\BaseEngineController_A02_bak2.map -srec=.\Target\BaseEngineController_A02_bak2.run -tdbver=1 -tdb=EriRequestTableList -crctable=g_pCRCBlockPtr -InitialisedRAM=.fixed_ramcals,.fixed_romcals -InitialisedRAM=.ramcals,.romcals -InitialisedRAM=.sdata,.romsdata -out=BaseEngineController_A02_bak2.sr -TransformBetween=0x00400000-0x0041FFFF -TransformBetween=0x00000000-0x0006FFFF -toolchain=GCC -InitialisedRAM=.data,.romdata -encrypt=.\Target\BaseEngineController_A02_bak2_119.srz</Execute>
			<Order>55</Order>
		</Command>
		<Compiler>
			<Define name="REAL_T" value="float"/>
			<Define name="TIME_T" value="float"/>
			<Define name="DISALLOW_TDB_DEFINES" value="1"/>
			<Define name="RES_NONE" value="-1"/>
			<GenerateListFiles>false</GenerateListFiles>
		</Compiler>
		<BuildStats>
			<Symbol>BaseEngineController_A02_bak2_M</Symbol>
			<Symbol>BaseEngineController_A02_bak2_B</Symbol>
			<Symbol>BaseEngineController_A02_bak2_DWork</Symbol>
			<Symbol>BaseEngineController_A02_bak2_PrevZC</Symbol>
			<Symbol>BaseEngineController_A02_bak2_M_</Symbol>
			<Symbol>VolatileWork</Symbol>
			<Symbol>ConstantWork</Symbol>
			<Symbol>NonVolatileWork</Symbol>
			<Symbol>NonVolatileDefault</Symbol>
			<Symbol>FgndTimeStack</Symbol>
			<Symbol>FgndAngleStack</Symbol>
			<Symbol>BgndStack</Symbol>
			<Symbol>IdleStack</Symbol>
			<Symbol>InterruptStack</Symbol>
			<Symbol>Heap</Symbol>
			<Symbol>Stack</Symbol>
			<Symbol>BaseEngineController_A02_bak2_Foreground</Symbol>
		</BuildStats>
		<Command>
			<Order>-10000</Order>
			<Execute>@if exist .\rtwtypes.h del /Q /F .\rtwtypes.h &gt; NUL</Execute>
		</Command>
	</Build>
	<Signature>0f29ead8-96da-4e46-9b-48-67-f6-e5-e1-64</Signature>
</Application>